sql2func/__about__.py
sql2func/__init__.py
sql2func/_engine.py
sql2func/_typing.py
sql2func/context.py
sql2func/dbapi2.py
sql2func/decorator.py
sql2func/exception.py
sql2func/py.typed
sql2func/_compat/__init__.py
sql2func/_compat/_pydantic.py
sql2func/template/__init__.py
sql2func/template/_compiler.py
sql2func/template/_lexer.py
sql2func/template/_nodes.py
sql2func/template/_renderer.py
sql2func/template/_template.py
sql2func-0.0.1.dev3.dist-info/METADATA
sql2func-0.0.1.dev3.dist-info/WHEEL
sql2func-0.0.1.dev3.dist-info/licenses/LICENSE
sql2func-0.0.1.dev3.dist-info/RECORD
