Metadata-Version: 2.4
Name: sql2func
Version: 0.0.1.dev3
Summary: Run SQL as a function.
Project-URL: Homepage, https://github.com/deadblue/sql2func
Author-email: Tomo Kunagisa <root@dead.blue>
License: MIT License
License-File: LICENSE
Classifier: Development Status :: 3 - Alpha
Classifier: License :: OSI Approved :: MIT License
Classifier: Operating System :: OS Independent
Classifier: Programming Language :: Python
Classifier: Programming Language :: Python :: 3
Classifier: Programming Language :: Python :: 3.10
Classifier: Programming Language :: Python :: 3.11
Classifier: Programming Language :: Python :: 3.12
Classifier: Topic :: Database
Requires-Python: >=3.10
Requires-Dist: jinja2<4,>=3.0.0
Provides-Extra: pydantic
Requires-Dist: pydantic<3,>=2.0.0; extra == 'pydantic'
